urso/__init__.py
urso/__main__.py
urso/base.py
urso-1.0.dist-info/LICENSE
urso-1.0.dist-info/METADATA
urso-1.0.dist-info/WHEEL
urso-1.0.dist-info/top_level.txt
urso-1.0.dist-info/RECORD
