Metadata-Version: 2.1
Name: urso
Version: 1.0
Summary: Random Content Generator
Author: Humberto Barrantes
Author-email: sudohumberto@gmail.com
Classifier: License :: OSI Approved :: MIT License
Classifier: Programming Language :: Python :: 3
Classifier: Programming Language :: Python :: 3.9
Classifier: Operating System :: OS Independent
Requires-Python: >=3.6
License-File: LICENSE
Requires-Dist: cffi (==1.15.1)
Requires-Dist: numpy (==1.24.3)
Requires-Dist: opencv-python (==4.7.0.72)
Requires-Dist: pycparser (==2.21)
Requires-Dist: soundfile (==0.12.1)
